nonebot_plugin_error_alert/__init__.py
nonebot_plugin_error_alert/alert.py
nonebot_plugin_error_alert/config.py
nonebot_plugin_error_alert/matcher.py
nonebot_plugin_error_alert/subscribe.py
nonebot_plugin_error_alert-0.2.0.dist-info/METADATA
nonebot_plugin_error_alert-0.2.0.dist-info/WHEEL
nonebot_plugin_error_alert-0.2.0.dist-info/RECORD
