Metadata-Version: 2.1
Name: nonebot-plugin-error-alert
Version: 0.2.0
Summary: 
License: MIT
Author: ssttkkl
Author-email: huang.wen.long@hotmail.com
Requires-Python: >=3.9,<4.0
Classifier: License :: OSI Approved :: MIT License
Classifier: Programming Language :: Python :: 3
Classifier: Programming Language :: Python :: 3.9
Classifier: Programming Language :: Python :: 3.10
Classifier: Programming Language :: Python :: 3.11
Requires-Dist: nb-cli (>=1.2.3,<2.0.0)
Requires-Dist: nonebot-plugin-apscheduler (>=0.3.0)
Requires-Dist: nonebot-plugin-datastore (>=1.0.0)
Requires-Dist: nonebot-plugin-send-anything-anywhere (>=0.3.0)
Requires-Dist: nonebot2 (>=2.0.0,<3.0.0)
